renardo_gatherer/__init__.py
renardo_gatherer/config_dir.py
renardo_gatherer/samples_download.py
renardo_gatherer-0.1.3.dist-info/METADATA
renardo_gatherer-0.1.3.dist-info/WHEEL
renardo_gatherer-0.1.3.dist-info/entry_points.txt
renardo_gatherer-0.1.3.dist-info/top_level.txt
renardo_gatherer-0.1.3.dist-info/RECORD
