Metadata-Version: 2.1
Name: renardo_gatherer
Version: 0.1.3
Summary: Asset collector for Renardo Python livecoding environment
Home-page: http://renardo.org/
Author: Elie Gavoty
Author-email: eliegavoty@free.fr
License: cc-by-sa-4.0
Requires-Dist: requests
Requires-Dist: beautifulsoup4
Requires-Dist: indexed
